parsedatetime/__init__.py
parsedatetime/context.py
parsedatetime/parsedatetime.py
parsedatetime/warns.py
parsedatetime/pdt_locales/__init__.py
parsedatetime/pdt_locales/base.py
parsedatetime/pdt_locales/de_DE.py
parsedatetime/pdt_locales/en_AU.py
parsedatetime/pdt_locales/en_US.py
parsedatetime/pdt_locales/es.py
parsedatetime/pdt_locales/fr_FR.py
parsedatetime/pdt_locales/icu.py
parsedatetime/pdt_locales/nl_NL.py
parsedatetime/pdt_locales/pt_BR.py
parsedatetime/pdt_locales/ru_RU.py
parsedatetime-2.3.dist-info/DESCRIPTION.rst
parsedatetime-2.3.dist-info/METADATA
parsedatetime-2.3.dist-info/RECORD
parsedatetime-2.3.dist-info/WHEEL
parsedatetime-2.3.dist-info/metadata.json
parsedatetime-2.3.dist-info/pbr.json
parsedatetime-2.3.dist-info/top_level.txt
