Metadata-Version: 1.1
Name: parsedatetime
Version: 2.3
Summary: Parse human-readable date/time text.
Home-page: https://github.com/bear/parsedatetime
Author: Mike Taylor
Author-email: bear@bear.im
License: Apache License 2.0
Download-URL: https://pypi.python.org/pypi/parsedatetime
Platform: Any
Classifier: Development Status :: 5 - Production/Stable
Classifier: Intended Audience :: Developers
Classifier: License :: OSI Approved :: Apache Software License
Classifier: Operating System :: OS Independent
Classifier: Topic :: Text Processing
Classifier: Topic :: Software Development :: Libraries :: Python Modules
Classifier: Programming Language :: Python :: 2.7
Classifier: Programming Language :: Python :: 3
Classifier: Programming Language :: Python :: 3.3
Classifier: Programming Language :: Python :: 3.4
